shellous/__init__.py
shellous/command.py
shellous/harvest.py
shellous/log.py
shellous/pipeline.py
shellous/prompt.py
shellous/pty_util.py
shellous/py.typed
shellous/redirect.py
shellous/result.py
shellous/runner.py
shellous/util.py
shellous-0.39.0.dist-info/LICENSE
shellous-0.39.0.dist-info/METADATA
shellous-0.39.0.dist-info/WHEEL
shellous-0.39.0.dist-info/RECORD
