Metadata-Version: 2.3
Name: shellous
Version: 0.39.0
Summary: Async Processes and Pipelines
License: Apache-2.0
Author: Bill Fisher
Author-email: william.w.fisher@gmail.com
Requires-Python: >=3.9,<4.0
Classifier: Development Status :: 5 - Production/Stable
Classifier: Framework :: AsyncIO
Classifier: Intended Audience :: Developers
Classifier: Intended Audience :: System Administrators
Classifier: License :: OSI Approved :: Apache Software License
Classifier: Operating System :: OS Independent
Classifier: Programming Language :: Python :: 3
Classifier: Programming Language :: Python :: 3.9
Classifier: Programming Language :: Python :: 3.10
Classifier: Programming Language :: Python :: 3.11
Classifier: Programming Language :: Python :: 3.12
Classifier: Programming Language :: Python :: 3.13
Classifier: Programming Language :: Python :: 3.14
Classifier: Typing :: Typed
Project-URL: Homepage, https://github.com/byllyfish/shellous
Project-URL: Issue Tracker, https://github.com/byllyfish/shellous/issues
Project-URL: Release Notes, https://github.com/byllyfish/shellous/blob/main/CHANGELOG.md
